{
	"animations": [
		{
			"loop": true,
			"offsets": [
				55,
				13
			],
			"anim": "singLEFTmiss",
			"fps": 24,
			"name": "BF NOTE LEFT MISS",
			"indices": []
		},
		{
			"loop": true,
			"offsets": [
				56,
				-72
			],
			"anim": "singDOWNmiss",
			"fps": 24,
			"name": "BF NOTE DOWN MISS",
			"indices": []
		},
		{
			"loop": true,
			"offsets": [
				48,
				36
			],
			"anim": "singUPmiss",
			"fps": 24,
			"name": "BF NOTE UP MISS",
			"indices": []
		},
		{
			"loop": true,
			"offsets": [
				3,
				11
			],
			"anim": "singRIGHTmiss",
			"fps": 24,
			"name": "BF NOTE RIGHT MISS",
			"indices": []
		},
		{
			"offsets": [
				56,
				11
			],
			"indices": [],
			"fps": 24,
			"anim": "idle",
			"loop": true,
			"name": "BF Super idle dance instance 1"
		},
		{
			"offsets": [
				64,
				14
			],
			"indices": [],
			"fps": 24,
			"anim": "singLEFT",
			"loop": true,
			"name": "BF NOTE LEFT instance 1"
		},
		{
			"offsets": [
				60,
				-71
			],
			"indices": [],
			"fps": 24,
			"anim": "singDOWN",
			"loop": true,
			"name": "BF NOTE DOWN instance 1"
		},
		{
			"offsets": [
				51,
				40
			],
			"indices": [],
			"fps": 24,
			"anim": "singUP",
			"loop": true,
			"name": "BF NOTE UP instance 1"
		},
		{
			"offsets": [
				13,
				9
			],
			"indices": [],
			"fps": 24,
			"anim": "singRIGHT",
			"loop": true,
			"name": "BF NOTE RIGHT instance 1"
		}
	],
	"no_antialiasing": false,
	"image": "characters/Super_BoyFriend_Assets",
	"position": [
		0,
		350
	],
	"healthicon": "bf",
	"flip_x": true,
	"healthbar_colors": [
		49,
		176,
		209
	],
	"camera_position": [
		-100,
		0
	],
	"sing_duration": 4,
	"scale": 1
}